minical/__init__.py
minical/__main__.py
minical/add.py
minical/app.py
minical/errors.py
minical/event_template.txt
minical/util.py
minical/validate_file.py
minical/whats_next.py
minical/templates/edit_event.html
minical/templates/events.html
minical/templates/new_event.html
minical-0.0.2.dist-info/METADATA
minical-0.0.2.dist-info/WHEEL
minical-0.0.2.dist-info/entry_points.txt
minical-0.0.2.dist-info/top_level.txt
minical-0.0.2.dist-info/RECORD
