Metadata-Version: 2.1
Name: minical
Version: 0.0.2
Summary: extremely basic calendar, with app and cli interfaces, and simple file format
Home-page: https://git.sr.ht/~dancromartie/minical
Author: Dan Cromartie
Classifier: Programming Language :: Python :: 3
Classifier: License :: OSI Approved :: MIT License
Classifier: Operating System :: OS Independent
Requires-Python: >=3.6
Requires-Dist: flask
Requires-Dist: gunicorn
